.gitignore
README
README.rst
bootstrap.py
buildout.cfg
jenkins.cfg
pre-commit-check.sh
setup.py
collective/__init__.py
collective.table.egg-info/PKG-INFO
collective.table.egg-info/SOURCES.txt
collective.table.egg-info/dependency_links.txt
collective.table.egg-info/entry_points.txt
collective.table.egg-info/namespace_packages.txt
collective.table.egg-info/not-zip-safe
collective.table.egg-info/requires.txt
collective.table.egg-info/top_level.txt
collective/table/__init__.py
collective/table/config.py
collective/table/configure.zcml
collective/table/field_widget.py
collective/table/interfaces.py
collective/table/local.py
collective/table/source.py
collective/table/sources.zcml
collective/table/table.py
collective/table/browser/__init__.py
collective/table/browser/configure.zcml
collective/table/browser/local.py
collective/table/browser/source.py
collective/table/browser/table.py
collective/table/browser/resources/collective.table.css
collective/table/browser/resources/collective.table.js
collective/table/browser/resources/jquery.jeditable.js
collective/table/browser/templates/table_macros.pt
collective/table/locales/collective.table.pot
collective/table/profiles/default/factorytool.xml
collective/table/profiles/default/jsregistry.xml
collective/table/profiles/default/metadata.xml
collective/table/profiles/default/rolemap.xml
collective/table/profiles/default/types.xml
collective/table/profiles/default/types/Table.xml
collective/table/tests/__init__.py
collective/table/tests/_test_selenium.py
collective/table/tests/base.py
collective/table/tests/test_local.py
collective/table/tests/test_setup.py
collective/table/tests/test_table.py
collective/table/tests/test_table_widget.py
docs/CREDITS.txt
docs/FUTURE.txt
docs/HISTORY.txt
docs/LICENSE.GPL
docs/LICENSE.txt
docs/sphinx/api.rst
docs/sphinx/conf.py
docs/sphinx/dev.rst
docs/sphinx/glossary.rst
docs/sphinx/index.rst