Metadata-Version: 1.0
Name: collective.table
Version: 1.1.1
Summary: Table-like content for Plone
Home-page: http://github.com/collective/collective.table
Author: Jarn AS
Author-email: info@jarn.com
License: GPL
Keywords: plone table data
Platform: UNKNOWN
Classifier: Programming Language :: Python
Classifier: Programming Language :: JavaScript
Classifier: Framework :: Plone
Classifier: License :: OSI Approved :: GNU General Public License (GPL)
